ec2instances/__init__.py
ec2instances/ec2_instance_mapping.py
ec2instances/ec2_instance_proxy.py
ec2instances/common/__init__.py
ec2instances/common/session.py
ec2instances/common/signal_handler.py
ec2instances/common/user_data.py
ec2map-1.0.15.dist-info/LICENSE.md
ec2map-1.0.15.dist-info/WHEEL
ec2map-1.0.15.dist-info/METADATA
ec2map-1.0.15.dist-info/RECORD
